DevGoldy/__init__.py
DevGoldy/errors.py
DevGoldy/cli/__init__.py
DevGoldy/cli/commands/__init__.py
DevGoldy/cli/commands/fix.py
DevGoldy/cli/commands/reload.py
DevGoldy/cli/commands/usb.py
DevGoldy/utils/__init__.py
DevGoldy/utils/powershell.py
DevGoldy-1.3.2.dist-info/METADATA
DevGoldy-1.3.2.dist-info/WHEEL
DevGoldy-1.3.2.dist-info/entry_points.txt
DevGoldy-1.3.2.dist-info/top_level.txt
DevGoldy-1.3.2.dist-info/RECORD
